clinform/__init__.py
clinform-0.0.0a1.dist-info/METADATA
clinform-0.0.0a1.dist-info/WHEEL
clinform-0.0.0a1.dist-info/top_level.txt
clinform-0.0.0a1.dist-info/RECORD
